xTool/__init__.py
xTool/exceptions.py
xTool/git_version
xTool/misc.py
xTool/plugins_manager.py
xTool/processes.py
xTool/stats.py
xTool/status.py
xTool/version.py
xTool/algorithms/__init__.py
xTool/algorithms/graphs/__init__.py
xTool/algorithms/graphs/sort.py
xTool/crypto/__init__.py
xTool/crypto/fernet.py
xTool/db/__init__.py
xTool/db/alchemy_orm.py
xTool/decorators/__init__.py
xTool/decorators/db.py
xTool/decorators/decorators.py
xTool/executors/__init__.py
xTool/executors/base_executor.py
xTool/executors/celery_executor.py
xTool/executors/dask_executor.py
xTool/executors/local_executor.py
xTool/executors/sequential_executor.py
xTool/rules/__init__.py
xTool/rules/trigger_rule.py
xTool/rules/weight_rule.py
xTool/task/__init__.py
xTool/task/task_runner/__init__.py
xTool/task/task_runner/base_task_runner.py
xTool/task/task_runner/bash_task_runner.py
xTool/ti_deps/__init__.py
xTool/ti_deps/deps/__init__.py
xTool/ti_deps/deps/base_ti_dep.py
xTool/utils/__init__.py
xTool/utils/asciiart.py
xTool/utils/cli.py
xTool/utils/compression.py
xTool/utils/configuration.py
xTool/utils/dates.py
xTool/utils/file.py
xTool/utils/file_processing.py
xTool/utils/helpers.py
xTool/utils/module_loading.py
xTool/utils/net.py
xTool/utils/operator_resources.py
xTool/utils/processes.py
xTool/utils/signal_handler.py
xTool/utils/state.py
xTool/utils/tests.py
xTool/utils/timeout.py
xTool/utils/timezone.py
xTool/utils/log/__init__.py
xTool/utils/log/logging_mixin.py
xTool-0.0.1.dist-info/LICENSE
xTool-0.0.1.dist-info/METADATA
xTool-0.0.1.dist-info/WHEEL
xTool-0.0.1.dist-info/top_level.txt
xTool-0.0.1.dist-info/RECORD
